aicsapi_tool_python/__init__.py
aicsapi_tool_python/appinsight_transport.py
aicsapi_tool_python/keyvault_certgen.py
aicsapi_tool_python/keyvault_tokenCache.py
aicsapi_tool_python/keyvault_utils.py
aicsapi_tool_python-0.3.2.dist-info/LICENSE
aicsapi_tool_python-0.3.2.dist-info/METADATA
aicsapi_tool_python-0.3.2.dist-info/WHEEL
aicsapi_tool_python-0.3.2.dist-info/top_level.txt
aicsapi_tool_python-0.3.2.dist-info/RECORD
