Metadata-Version: 2.1
Name: aicsapi-tool-python
Version: 0.3.2
Summary: Toolkit for Python backend template
Home-page: https://github.com/ASUS-AICS/aicsapi-tool-python
Author: Sean (Shih-Lun) Wu
Author-email: summer7sean@gmail.com
License: UNKNOWN
Platform: UNKNOWN
Classifier: Programming Language :: Python :: 3.7
Classifier: License :: OSI Approved :: MIT License
Requires-Dist: applicationinsights (==0.11.9)
Requires-Dist: adal (==1.0.2)
Requires-Dist: python-dotenv (==0.10.3)
Requires-Dist: azure-keyvault (==1.1.0)
Requires-Dist: pyOpenSSL (==19.0.0)
